authanon/__init__.py
authanon/apps.py
authanon/backends.py
authanon/management/commands/authanon.py
authanon/migrations/__init__.py
django_authanon-0.1.2.dist-info/LICENSE
django_authanon-0.1.2.dist-info/WHEEL
django_authanon-0.1.2.dist-info/METADATA
django_authanon-0.1.2.dist-info/RECORD
