Metadata-Version: 2.1
Name: django-authanon
Version: 0.1.2
Summary: Allows permissions for an anonymous user and a generic signed-in user to be set as groups.
Home-page: https://github.com/rbturnbull/django-authanon
License: Apache 2.0
Author: Robert Turnbull
Author-email: robert.turnbull@unimelb.edu.au
Requires-Python: >=3.7.1,<4.0.0
Classifier: License :: Other/Proprietary License
Classifier: Programming Language :: Python :: 3
Classifier: Programming Language :: Python :: 3.10
Classifier: Programming Language :: Python :: 3.8
Classifier: Programming Language :: Python :: 3.9
Requires-Dist: Django (>=3.0,<4.0)
Project-URL: Repository, https://github.com/rbturnbull/django-authanon
